pymolviz/ColorMap.py
pymolviz/Displayable.py
pymolviz/Group.py
pymolviz/Script.py
pymolviz/__init__.py
pymolviz/PyMOLobjects/Expressions.py
pymolviz/PyMOLobjects/Label2D.py
pymolviz/PyMOLobjects/Labels.py
pymolviz/PyMOLobjects/PseudoAtoms.py
pymolviz/PyMOLobjects/__init__.py
pymolviz/meshes/Arrows.py
pymolviz/meshes/CGOCollection.py
pymolviz/meshes/CGOMolecule.py
pymolviz/meshes/CenteredBox.py
pymolviz/meshes/ConvexHull.py
pymolviz/meshes/Cylinder.py
pymolviz/meshes/Lines.py
pymolviz/meshes/Mesh.py
pymolviz/meshes/Plane.py
pymolviz/meshes/Points.py
pymolviz/meshes/Sphere.py
pymolviz/meshes/__init__.py
pymolviz/meshes/derived/Rotation_Indicator.py
pymolviz/meshes/derived/__init__.py
pymolviz/methods/__init__.py
pymolviz/methods/docking.py
pymolviz/util/ViewportCallback.py
pymolviz/util/__init__.py
pymolviz/util/colors.py
pymolviz/util/geometries.py
pymolviz/util/io.py
pymolviz/util/math.py
pymolviz/util/pymol_functions.py
pymolviz/util/sanitize.py
pymolviz/util/vector_functions.py
pymolviz/volumetric/ColorRamp.py
pymolviz/volumetric/GridData.py
pymolviz/volumetric/IsoMesh.py
pymolviz/volumetric/IsoSurface.py
pymolviz/volumetric/IsoVolume.py
pymolviz/volumetric/Volume.py
pymolviz/volumetric/__init__.py
pymolviz-1.3.1.dist-info/METADATA
pymolviz-1.3.1.dist-info/WHEEL
pymolviz-1.3.1.dist-info/top_level.txt
pymolviz-1.3.1.dist-info/RECORD
