Metadata-Version: 2.1
Name: pymolviz
Version: 1.3.1
Summary: Library to facilitate creation of PyMOL Vizualizations.
Home-page: https://github.com/Finnem/PyMolViz
Author: Finn Mier
License: MIT
Requires-Dist: numpy
Requires-Dist: matplotlib
Requires-Dist: scipy
Requires-Dist: pandas
Requires-Dist: cmap
